calc_elastic_constants.py
calc_elastic_elate.py
calc_stress.py
christoffel.py
deform_cell_asess_strains.py
deform_cell_ohess_strains.py
deform_cell_ulics.py
elastool_elate_browser.py
elastoolgui.py
elate.py
equilibrium_md.py
extract_mean_values.py
find_spg.py
make_conv_cell.py
material_analysis.py
optimize_initial_str.py
plot_christoffel_gnu.py
plotchristoffel.py
predict_thickness_2D.py
read_flags.py
read_help.py
read_input.py
relax_atoms_pos.py
sound_velocity.py
stability_criteria.py
strain_matrix.py
vasp_run.py
view_file.py
write_default_input.py
write_incar.py
elastool-3.80.data/scripts/elastool
elastool-3.80.dist-info/LICENSE
elastool-3.80.dist-info/METADATA
elastool-3.80.dist-info/WHEEL
elastool-3.80.dist-info/top_level.txt
elastool-3.80.dist-info/RECORD
