Metadata-Version: 2.1
Name: elastool
Version: 3.80
Summary: Elastic tool for zero and finite-temperature elastic constants and mechanical properties calculations
Home-page: https://sourceforge.net/projects/elastool/
Author: Zhong-Li Liu and Chinedu Ekuma
Author-email: cekuma1@gmail.com
License: GNU GPL version 3
License-File: LICENSE
Requires-Dist: numpy >=1.20.0
Requires-Dist: scipy >=1.11.0
Requires-Dist: matplotlib >=3.8.0
Requires-Dist: pandas >=1.5.0
Requires-Dist: seaborn >=0.13.0
Requires-Dist: pymatgen >=2023.10.11
Requires-Dist: kaleido >=0.2.1
Requires-Dist: plotly >=5.18.0
Requires-Dist: spglib >=2.1.0
Requires-Dist: ase >=3.22.1
Requires-Dist: pyvista >=0.42.3
Requires-Dist: selenium >=4.14.0
Requires-Dist: catboost >=1.2.2
Requires-Dist: matminer >=0.9.2
Requires-Dist: scikit-learn >=1.3.2
Requires-Dist: tensorflow >=2.16.1
Requires-Dist: keras >=3.0.5
Requires-Dist: bayesian-optimization >=1.4.3
Requires-Dist: periodictable >=1.7.0
